clanguru/__init__.py
clanguru/_run.py
clanguru/compilation_options_manager.py
clanguru/cparser.py
clanguru/doc_generator.py
clanguru/main.py
clanguru/mock_generator.py
clanguru/object_analyzer.html.jinja
clanguru/object_analyzer.py
clanguru/py.typed
clanguru/templates/mock/gmock/header.h.j2
clanguru/templates/mock/gmock/source.cc.j2
clanguru-0.15.0.dist-info/METADATA
clanguru-0.15.0.dist-info/WHEEL
clanguru-0.15.0.dist-info/entry_points.txt
clanguru-0.15.0.dist-info/licenses/LICENSE
clanguru-0.15.0.dist-info/RECORD
