Metadata-Version: 2.4
Name: clanguru
Version: 0.15.0
Summary: C language utils and tools based on the clang and binutils modules.
License: MIT
License-File: LICENSE
Author: cuinixam
Author-email: me@cuinixam.me
Requires-Python: <4.0,>=3.10
Classifier: Development Status :: 2 - Pre-Alpha
Classifier: Intended Audience :: Developers
Classifier: Natural Language :: English
Classifier: Operating System :: OS Independent
Classifier: Programming Language :: Python :: 3.10
Classifier: Programming Language :: Python :: 3.11
Classifier: Programming Language :: Python :: 3.12
Classifier: Programming Language :: Python :: 3.13
Classifier: Topic :: Software Development :: Libraries
Requires-Dist: jinja2 (>=3.1,<4)
Requires-Dist: libclang (>=18.1,<19)
Requires-Dist: mashumaro (>=3.13,<4)
Requires-Dist: openpyxl (>=3.1,<4)
Requires-Dist: py-app-dev (>=2.1,<3)
Requires-Dist: pyyaml (>=6,<7)
Requires-Dist: typer (>=0,<1)
Project-URL: Bug Tracker, https://github.com/cuinixam/clanguru/issues
Project-URL: Changelog, https://github.com/cuinixam/clanguru/blob/main/CHANGELOG.md
Project-URL: Repository, https://github.com/cuinixam/clanguru
